odoo/addons/l10n_it_intrastat/README.rst
odoo/addons/l10n_it_intrastat/__init__.py
odoo/addons/l10n_it_intrastat/__manifest__.py
odoo/addons/l10n_it_intrastat/data/account.intrastat.custom.csv
odoo/addons/l10n_it_intrastat/data/account.intrastat.transaction.nature.b.csv
odoo/addons/l10n_it_intrastat/data/account.intrastat.transaction.nature.csv
odoo/addons/l10n_it_intrastat/data/account.intrastat.transport.csv
odoo/addons/l10n_it_intrastat/data/report.intrastat.code.csv
odoo/addons/l10n_it_intrastat/demo/product_demo.xml
odoo/addons/l10n_it_intrastat/i18n/es.po
odoo/addons/l10n_it_intrastat/i18n/it.po
odoo/addons/l10n_it_intrastat/i18n/l10n_it_intrastat.pot
odoo/addons/l10n_it_intrastat/migrations/12.0.1.0.0/pre-migrate.py
odoo/addons/l10n_it_intrastat/migrations/13.0.1.0.0/pre-migrate.py
odoo/addons/l10n_it_intrastat/models/__init__.py
odoo/addons/l10n_it_intrastat/models/account.py
odoo/addons/l10n_it_intrastat/models/config.py
odoo/addons/l10n_it_intrastat/models/intrastat.py
odoo/addons/l10n_it_intrastat/models/product.py
odoo/addons/l10n_it_intrastat/readme/CONFIGURE.rst
odoo/addons/l10n_it_intrastat/readme/CONTRIBUTORS.rst
odoo/addons/l10n_it_intrastat/readme/DESCRIPTION.rst
odoo/addons/l10n_it_intrastat/readme/USAGE.rst
odoo/addons/l10n_it_intrastat/security/intrastat_rules.xml
odoo/addons/l10n_it_intrastat/security/ir.model.access.csv
odoo/addons/l10n_it_intrastat/static/description/icon.png
odoo/addons/l10n_it_intrastat/static/description/index.html
odoo/addons/l10n_it_intrastat/tests/__init__.py
odoo/addons/l10n_it_intrastat/tests/test_intrastat.py
odoo/addons/l10n_it_intrastat/views/account.xml
odoo/addons/l10n_it_intrastat/views/config.xml
odoo/addons/l10n_it_intrastat/views/intrastat.xml
odoo/addons/l10n_it_intrastat/views/product.xml
odoo14_addon_l10n_it_intrastat-14.0.1.6.0.dist-info/METADATA
odoo14_addon_l10n_it_intrastat-14.0.1.6.0.dist-info/WHEEL
odoo14_addon_l10n_it_intrastat-14.0.1.6.0.dist-info/top_level.txt
odoo14_addon_l10n_it_intrastat-14.0.1.6.0.dist-info/RECORD
