Metadata-Version: 2.1
Name: odoo14-addon-l10n_it_intrastat
Version: 14.0.1.6.0
Summary: Riclassificazione merci e servizi per dichiarazioni Intrastat
Home-page: https://github.com/OCA/l10n-italy
Author: Openforce, Link IT srl, Agile Business Group, Powerp network, Odoo Community Association (OCA)
Author-email: support@odoo-community.org
License: AGPL-3
Classifier: Programming Language :: Python
Classifier: Framework :: Odoo
Classifier: Framework :: Odoo :: 14.0
Classifier: License :: OSI Approved :: GNU Affero General Public License v3
Requires-Python: >=3.6
Requires-Dist: odoo14-addon-web-widget-char-size
Requires-Dist: odoo<14.1dev,>=14.0a
